qff/__init__.py
qff/__main__.py
qff/config.ts.json
qff/frame/__init__.py
qff/frame/api.py
qff/frame/backtest.py
qff/frame/backup.py
qff/frame/cli.py
qff/frame/const.py
qff/frame/context.py
qff/frame/evaluation.py
qff/frame/order.py
qff/frame/perf.py
qff/frame/portfolio.py
qff/frame/position.py
qff/frame/settle.py
qff/frame/simtrade.py
qff/frame/stats.py
qff/frame/template.html
qff/frame/trace.py
qff/helper/__init__.py
qff/helper/common.py
qff/helper/formula.py
qff/helper/indicator.py
qff/helper/ts.py
qff/price/__init__.py
qff/price/cache.py
qff/price/crawl.py
qff/price/fetch.py
qff/price/finance.py
qff/price/query.py
qff/store/__init__.py
qff/store/save_info.py
qff/store/save_mtss.py
qff/store/save_price.py
qff/store/save_report.py
qff/store/save_valuation.py
qff/store/update_all.py
qff/tools/__init__.py
qff/tools/config.py
qff/tools/date.py
qff/tools/email.py
qff/tools/kshow.py
qff/tools/local.py
qff/tools/logs.py
qff/tools/mongo.py
qff/tools/tdx.py
qff/tools/utils.py
qff/tools/word.py
qff/trader/__init__.py
qff/trader/ths.py
qff-0.5.19.dist-info/LICENSE
qff-0.5.19.dist-info/METADATA
qff-0.5.19.dist-info/WHEEL
qff-0.5.19.dist-info/entry_points.txt
qff-0.5.19.dist-info/top_level.txt
qff-0.5.19.dist-info/zip-safe
qff-0.5.19.dist-info/RECORD
