Metadata-Version: 2.1
Name: qff
Version: 0.5.19
Summary: qff: quantize finance framework
Home-page: https://github.com/haijiangxu/qff
Author: xuhaijiang
Author-email: haijiangxu@hotmail.com
License: MIT
Keywords: QFF,stock,quant,quantize,finance,backtest,trading,investment,JoinQuant
Classifier: Development Status :: 3 - Alpha
Classifier: License :: OSI Approved :: MIT License
Classifier: Programming Language :: Python
Classifier: Intended Audience :: Developers
Classifier: Operating System :: OS Independent
Classifier: Programming Language :: Python :: 3.7
Classifier: Programming Language :: Python :: 3.8
Classifier: Programming Language :: Python :: 3.9
Classifier: Programming Language :: Python :: 3.10
Requires-Python: >=3.7
License-File: LICENSE
Requires-Dist: pandas>=1.5.1
Requires-Dist: zenlog~=1.1
Requires-Dist: numpy>=1.23.5
Requires-Dist: matplotlib>=3.4.3
Requires-Dist: pytdx~=1.72
Requires-Dist: pymongo~=3.12.0
Requires-Dist: pyecharts~=2.0.1
Requires-Dist: requests>=2.26.0
Requires-Dist: prettytable~=2.2.0
Requires-Dist: akshare>=1.9.6
Requires-Dist: python-dateutil~=2.8.2
Requires-Dist: empyrical==0.5.5
Requires-Dist: Jinja2==3.1.2
Requires-Dist: beautifulsoup4~=4.11.1
Requires-Dist: retrying~=1.3.3
Requires-Dist: python-docx~=0.8.11
Requires-Dist: Pillow~=9.4.0
Requires-Dist: ddddocr==1.4.7
Requires-Dist: setuptools==62.2.0
Requires-Dist: pywinauto==0.6.8; platform_system == "Windows"
